safe_exit/__init__.py
safe_exit-0.1.2.dist-info/LICENSE.txt
safe_exit-0.1.2.dist-info/METADATA
safe_exit-0.1.2.dist-info/WHEEL
safe_exit-0.1.2.dist-info/top_level.txt
safe_exit-0.1.2.dist-info/RECORD
