Metadata-Version: 2.1
Name: safe-exit
Version: 0.1.2
Summary: Handle graceful process termination
Home-page: https://github.com/ZhangJianAo/safe-exit
Author: Zhang JianAo
Author-email: zhangjianao@gmail.com
License: MIT
Classifier: Development Status :: 6 - Mature
Classifier: License :: OSI Approved :: MIT License
Classifier: Programming Language :: Python :: 3
License-File: LICENSE.txt
Requires-Dist: psutil
